graphistry_mcp_server/__init__.py
graphistry_mcp_server/py.typed
graphistry_mcp_server/server.py
iflow_mcp_graphistry_mcp_server-0.1.0.dist-info/licenses/LICENSE
iflow_mcp_graphistry_mcp_server-0.1.0.dist-info/METADATA
iflow_mcp_graphistry_mcp_server-0.1.0.dist-info/WHEEL
iflow_mcp_graphistry_mcp_server-0.1.0.dist-info/entry_points.txt
iflow_mcp_graphistry_mcp_server-0.1.0.dist-info/top_level.txt
iflow_mcp_graphistry_mcp_server-0.1.0.dist-info/RECORD
