Metadata-Version: 2.4
Name: iflow-mcp_graphistry-mcp-server
Version: 0.1.0
Summary: Graphistry MCP integration for GPU-accelerated graph visualization using FastMCP
Author: Graphistry Community
License: MIT
Classifier: Programming Language :: Python :: 3
Classifier: License :: OSI Approved :: MIT License
Classifier: Operating System :: OS Independent
Requires-Python: >=3.10
License-File: LICENSE
Requires-Dist: fastmcp>=2.2.6
Requires-Dist: graphistry
Requires-Dist: faiss-cpu
Requires-Dist: pandas
Requires-Dist: networkx
Requires-Dist: python-igraph
Requires-Dist: asyncio
Requires-Dist: uvicorn
Requires-Dist: python-louvain
Requires-Dist: python-dotenv
Requires-Dist: pytest
Requires-Dist: pytest-asyncio
Requires-Dist: duckdb>=1.4.1
Requires-Dist: umap-learn>=0.5.9.post2
Requires-Dist: scikit-learn>=1.7.2
Provides-Extra: dev
Requires-Dist: black; extra == "dev"
Requires-Dist: ruff; extra == "dev"
Requires-Dist: mypy; extra == "dev"
Provides-Extra: visualization
Requires-Dist: matplotlib>=3.5.0; extra == "visualization"
Requires-Dist: plotly>=5.10.0; extra == "visualization"
Requires-Dist: pygraphviz>=1.9; extra == "visualization"
Dynamic: license-file
Dynamic: requires-python
